google_search_cli
