Metadata-Version: 1.0
Name: google-search-cli
Version: 0.0.3
Summary: google search cli
Home-page: https://github.com/zweifisch/google-search-cli
Author: Feng Zhou
Author-email: zf.pascal@gmail.com
License: MIT
Keywords: google search cli
Platform: UNKNOWN
Classifier: Development Status :: 3 - Alpha
Classifier: License :: OSI Approved :: MIT License
Classifier: Programming Language :: Python :: 2.7
Classifier: Programming Language :: Python :: 3.4
